pts_hipot_tester/__init__.py
pts_hipot_tester/st9201_hipot_tester.py
pts_hipot_tester-0.0.9.dist-info/LICENSE.txt
pts_hipot_tester-0.0.9.dist-info/METADATA
pts_hipot_tester-0.0.9.dist-info/WHEEL
pts_hipot_tester-0.0.9.dist-info/top_level.txt
pts_hipot_tester-0.0.9.dist-info/RECORD
